{
	"name": "MAIN",
	"new_element_type": "OR_3",
	"new_element_inputs_number": "3",
	"new_element_outputs_number": 1,
	"blocks": {
		"1": {
			"id": "INPUT_1",
			"type": "INPUT",
			"x": 341.203125,
			"y": 76,
			"dragging": false,
			"const_id": "1",
			"input_connectors_coordinates": [],
			"output_connectors_coordinates": [
				{
					"x": 545.796875,
					"y": 121
				}
			]
		},
		"2": {
			"id": "INPUT_2",
			"type": "INPUT",
			"x": 331.578125,
			"y": 398,
			"dragging": false,
			"const_id": "2",
			"input_connectors_coordinates": [],
			"output_connectors_coordinates": [
				{
					"x": 541.421875,
					"y": 443
				}
			]
		},
		"3": {
			"id": "INPUT_3",
			"type": "INPUT",
			"x": 332.75,
			"y": 702,
			"dragging": false,
			"const_id": "3",
			"input_connectors_coordinates": [],
			"output_connectors_coordinates": [
				{
					"x": 542.25,
					"y": 747
				}
			]
		},
		"4": {
			"id": "AND_1",
			"type": "AND",
			"x": 695.5390625,
			"y": -9,
			"dragging": false,
			"const_id": "4",
			"input_connectors_coordinates": [
				{
					"x": 740.53125,
					"y": 36
				},
				{
					"x": 740.53125,
					"y": 108
				}
			],
			"output_connectors_coordinates": [
				{
					"x": 905.453125,
					"y": 36
				}
			]
		},
		"5": {
			"id": "AND_2",
			"type": "AND",
			"x": 687.5390625,
			"y": 163,
			"dragging": false,
			"const_id": "5",
			"input_connectors_coordinates": [
				{
					"x": 732.53125,
					"y": 208
				},
				{
					"x": 732.53125,
					"y": 280
				}
			],
			"output_connectors_coordinates": [
				{
					"x": 897.453125,
					"y": 208
				}
			]
		},
		"6": {
			"id": "AND_3",
			"type": "AND",
			"x": 681.5390625,
			"y": 327,
			"dragging": false,
			"const_id": "6",
			"input_connectors_coordinates": [
				{
					"x": 726.53125,
					"y": 372
				},
				{
					"x": 726.53125,
					"y": 444
				}
			],
			"output_connectors_coordinates": [
				{
					"x": 891.453125,
					"y": 372
				}
			]
		},
		"7": {
			"id": "OR_3_1",
			"type": "OR_3",
			"x": 673.3359375,
			"y": 494,
			"dragging": false,
			"const_id": "7",
			"input_connectors_coordinates": [
				{
					"x": 718.328125,
					"y": 539
				},
				{
					"x": 718.328125,
					"y": 611
				},
				{
					"x": 718.328125,
					"y": 683
				}
			],
			"output_connectors_coordinates": [
				{
					"x": 891.65625,
					"y": 539
				}
			]
		},
		"8": {
			"id": "AND_3_1",
			"type": "AND_3",
			"x": 657.6953125,
			"y": 729,
			"dragging": false,
			"const_id": "8",
			"input_connectors_coordinates": [
				{
					"x": 702.6875,
					"y": 774
				},
				{
					"x": 702.6875,
					"y": 846
				},
				{
					"x": 702.6875,
					"y": 918
				}
			],
			"output_connectors_coordinates": [
				{
					"x": 899.296875,
					"y": 774
				}
			]
		},
		"9": {
			"id": "OR_3_2",
			"type": "OR_3",
			"x": 965.3359375,
			"y": 105,
			"dragging": false,
			"const_id": "9",
			"input_connectors_coordinates": [
				{
					"x": 1010.328125,
					"y": 150
				},
				{
					"x": 1010.328125,
					"y": 222
				},
				{
					"x": 1010.328125,
					"y": 294
				}
			],
			"output_connectors_coordinates": [
				{
					"x": 1183.65625,
					"y": 150
				}
			]
		},
		"10": {
			"id": "OUTPUT_1",
			"type": "OUTPUT",
			"x": 1296.25,
			"y": 111,
			"dragging": false,
			"const_id": "10",
			"input_connectors_coordinates": [
				{
					"x": 1341.25,
					"y": 156
				}
			],
			"output_connectors_coordinates": []
		},
		"11": {
			"id": "NOT_1",
			"type": "NOT",
			"x": 970.5546875,
			"y": 359,
			"dragging": false,
			"const_id": "11",
			"input_connectors_coordinates": [
				{
					"x": 1015.546875,
					"y": 404
				}
			],
			"output_connectors_coordinates": [
				{
					"x": 1174.4375,
					"y": 404
				}
			]
		},
		"12": {
			"id": "AND_4",
			"type": "AND",
			"x": 970.5390625,
			"y": 475,
			"dragging": false,
			"const_id": "12",
			"input_connectors_coordinates": [
				{
					"x": 1015.53125,
					"y": 520
				},
				{
					"x": 1015.53125,
					"y": 592
				}
			],
			"output_connectors_coordinates": [
				{
					"x": 1180.453125,
					"y": 520
				}
			]
		},
		"13": {
			"id": "OR_1",
			"type": "OR",
			"x": 983.1796875,
			"y": 657,
			"dragging": false,
			"const_id": "13",
			"input_connectors_coordinates": [
				{
					"x": 1028.171875,
					"y": 702
				},
				{
					"x": 1028.171875,
					"y": 774
				}
			],
			"output_connectors_coordinates": [
				{
					"x": 1169.8125,
					"y": 702
				}
			]
		},
		"14": {
			"id": "OUTPUT_2",
			"type": "OUTPUT",
			"x": 1307.625,
			"y": 642,
			"dragging": false,
			"const_id": "14",
			"input_connectors_coordinates": [
				{
					"x": 1352.625,
					"y": 687
				}
			],
			"output_connectors_coordinates": []
		}
	},
	"wires": {
		"0": {
			"id": 0,
			"from_block_const_id": "1",
			"to_block_const_id": "4",
			"from_output_id": 0,
			"to_input_id": 0,
			"from_point": {
				"x": 545.796875,
				"y": 121
			},
			"to_point": {
				"x": 740.53125,
				"y": 36
			}
		},
		"1": {
			"id": 1,
			"from_block_const_id": "1",
			"to_block_const_id": "5",
			"from_output_id": 0,
			"to_input_id": 0,
			"from_point": {
				"x": 545.796875,
				"y": 121
			},
			"to_point": {
				"x": 732.53125,
				"y": 208
			}
		},
		"2": {
			"id": 2,
			"from_block_const_id": "1",
			"to_block_const_id": "7",
			"from_output_id": 0,
			"to_input_id": 0,
			"from_point": {
				"x": 545.796875,
				"y": 121
			},
			"to_point": {
				"x": 718.328125,
				"y": 539
			}
		},
		"3": {
			"id": 3,
			"from_block_const_id": "1",
			"to_block_const_id": "8",
			"from_output_id": 0,
			"to_input_id": 0,
			"from_point": {
				"x": 545.796875,
				"y": 121
			},
			"to_point": {
				"x": 702.6875,
				"y": 774
			}
		},
		"4": {
			"id": 4,
			"from_block_const_id": "2",
			"to_block_const_id": "4",
			"from_output_id": 0,
			"to_input_id": 1,
			"from_point": {
				"x": 541.421875,
				"y": 443
			},
			"to_point": {
				"x": 740.53125,
				"y": 108
			}
		},
		"5": {
			"id": 5,
			"from_block_const_id": "2",
			"to_block_const_id": "6",
			"from_output_id": 0,
			"to_input_id": 1,
			"from_point": {
				"x": 541.421875,
				"y": 443
			},
			"to_point": {
				"x": 726.53125,
				"y": 444
			}
		},
		"6": {
			"id": 6,
			"from_block_const_id": "2",
			"to_block_const_id": "7",
			"from_output_id": 0,
			"to_input_id": 1,
			"from_point": {
				"x": 541.421875,
				"y": 443
			},
			"to_point": {
				"x": 718.328125,
				"y": 611
			}
		},
		"7": {
			"id": 7,
			"from_block_const_id": "2",
			"to_block_const_id": "8",
			"from_output_id": 0,
			"to_input_id": 1,
			"from_point": {
				"x": 541.421875,
				"y": 443
			},
			"to_point": {
				"x": 702.6875,
				"y": 846
			}
		},
		"8": {
			"id": 8,
			"from_block_const_id": "3",
			"to_block_const_id": "5",
			"from_output_id": 0,
			"to_input_id": 1,
			"from_point": {
				"x": 542.25,
				"y": 747
			},
			"to_point": {
				"x": 732.53125,
				"y": 280
			}
		},
		"9": {
			"id": 9,
			"from_block_const_id": "3",
			"to_block_const_id": "6",
			"from_output_id": 0,
			"to_input_id": 0,
			"from_point": {
				"x": 542.25,
				"y": 747
			},
			"to_point": {
				"x": 726.53125,
				"y": 372
			}
		},
		"10": {
			"id": 10,
			"from_block_const_id": "3",
			"to_block_const_id": "7",
			"from_output_id": 0,
			"to_input_id": 2,
			"from_point": {
				"x": 542.25,
				"y": 747
			},
			"to_point": {
				"x": 718.328125,
				"y": 683
			}
		},
		"11": {
			"id": 11,
			"from_block_const_id": "3",
			"to_block_const_id": "8",
			"from_output_id": 0,
			"to_input_id": 2,
			"from_point": {
				"x": 542.25,
				"y": 747
			},
			"to_point": {
				"x": 702.6875,
				"y": 918
			}
		},
		"12": {
			"id": 12,
			"from_block_const_id": "4",
			"to_block_const_id": "9",
			"from_output_id": 0,
			"to_input_id": 0,
			"from_point": {
				"x": 905.453125,
				"y": 36
			},
			"to_point": {
				"x": 1010.328125,
				"y": 150
			}
		},
		"13": {
			"id": 13,
			"from_block_const_id": "5",
			"to_block_const_id": "9",
			"from_output_id": 0,
			"to_input_id": 1,
			"from_point": {
				"x": 897.453125,
				"y": 208
			},
			"to_point": {
				"x": 1010.328125,
				"y": 222
			}
		},
		"14": {
			"id": 14,
			"from_block_const_id": "6",
			"to_block_const_id": "9",
			"from_output_id": 0,
			"to_input_id": 2,
			"from_point": {
				"x": 891.453125,
				"y": 372
			},
			"to_point": {
				"x": 1010.328125,
				"y": 294
			}
		},
		"15": {
			"id": 15,
			"from_block_const_id": "9",
			"to_block_const_id": "10",
			"from_output_id": 0,
			"to_input_id": 0,
			"from_point": {
				"x": 1183.65625,
				"y": 150
			},
			"to_point": {
				"x": 1341.25,
				"y": 156
			}
		},
		"16": {
			"id": 16,
			"from_block_const_id": "9",
			"to_block_const_id": "11",
			"from_output_id": 0,
			"to_input_id": 0,
			"from_point": {
				"x": 1183.65625,
				"y": 150
			},
			"to_point": {
				"x": 1015.546875,
				"y": 404
			}
		},
		"17": {
			"id": 17,
			"from_block_const_id": "11",
			"to_block_const_id": "12",
			"from_output_id": 0,
			"to_input_id": 0,
			"from_point": {
				"x": 1174.4375,
				"y": 404
			},
			"to_point": {
				"x": 1015.53125,
				"y": 520
			}
		},
		"18": {
			"id": 18,
			"from_block_const_id": "7",
			"to_block_const_id": "12",
			"from_output_id": 0,
			"to_input_id": 1,
			"from_point": {
				"x": 891.65625,
				"y": 539
			},
			"to_point": {
				"x": 1015.53125,
				"y": 592
			}
		},
		"19": {
			"id": 19,
			"from_block_const_id": "12",
			"to_block_const_id": "13",
			"from_output_id": 0,
			"to_input_id": 0,
			"from_point": {
				"x": 1180.453125,
				"y": 520
			},
			"to_point": {
				"x": 1028.171875,
				"y": 702
			}
		},
		"20": {
			"id": 20,
			"from_block_const_id": "8",
			"to_block_const_id": "13",
			"from_output_id": 0,
			"to_input_id": 1,
			"from_point": {
				"x": 899.296875,
				"y": 774
			},
			"to_point": {
				"x": 1028.171875,
				"y": 774
			}
		},
		"21": {
			"id": 21,
			"from_block_const_id": "13",
			"to_block_const_id": "14",
			"from_output_id": 0,
			"to_input_id": 0,
			"from_point": {
				"x": 1169.8125,
				"y": 702
			},
			"to_point": {
				"x": 1352.625,
				"y": 687
			}
		}
	},
	"tests": []
}